textmul/__init__.py
textmul/textmul.py
kusozako_text_multiplication-0.0.2.dist-info/METADATA
kusozako_text_multiplication-0.0.2.dist-info/WHEEL
kusozako_text_multiplication-0.0.2.dist-info/top_level.txt
kusozako_text_multiplication-0.0.2.dist-info/RECORD
