Metadata-Version: 2.1
Name: kusozako-text-multiplication
Version: 0.0.2
Summary: kusozako_text_multiplication: くそざこ文字列掛け算ツール
Home-page: https://github.com/nikawamikan/textmul
Author: nikawamikan
Maintainer: nikawamikan
License: UNKNOWN
Download-URL: https://github.com/nikawamikan/textmul
Platform: UNKNOWN
